nestedhyperboost/__init__ .py
nestedhyperboost/argument_quality.py
nestedhyperboost/method_select.py
nestedhyperboost/ncv_optimizer.py
nestedhyperboost/results.py
nestedhyperboost/catboost/__init__.py
nestedhyperboost/catboost/cat_ncv_classifier.py
nestedhyperboost/catboost/cat_ncv_regressor.py
nestedhyperboost/catboost/cat_params.py
nestedhyperboost/lightgbm/__init__.py
nestedhyperboost/lightgbm/lgb_ncv_classifier.py
nestedhyperboost/lightgbm/lgb_ncv_regressor.py
nestedhyperboost/lightgbm/lgb_params.py
nestedhyperboost/xgboost/__init__.py
nestedhyperboost/xgboost/xgb_ncv_classifier.py
nestedhyperboost/xgboost/xgb_ncv_regressor.py
nestedhyperboost/xgboost/xgb_params.py
nestedhyperboost-0.0.3.dist-info/LICENSE
nestedhyperboost-0.0.3.dist-info/METADATA
nestedhyperboost-0.0.3.dist-info/WHEEL
nestedhyperboost-0.0.3.dist-info/top_level.txt
nestedhyperboost-0.0.3.dist-info/RECORD
