Metadata-Version: 2.1
Name: nestedhyperboost
Version: 0.0.3
Summary: A wrapper for conducting Nested Cross-Validation with Bayesian Hyper-Parameter Optimized Gradient Boosting
Home-page: https://github.com/nickkunz/nestedhyperboost
Author: Nick Kunz
Author-email: nick.kunz@me.com
License: UNKNOWN
Keywords: nested cross-validation,bayesian optimization,gradient boosting,xgboost,lightgbm,catboost
Platform: UNKNOWN
Classifier: Programming Language :: Python :: 3
Classifier: Intended Audience :: Science/Research
Classifier: Topic :: Scientific/Engineering
Classifier: Topic :: Scientific/Engineering :: Mathematics
Classifier: Topic :: Scientific/Engineering :: Artificial Intelligence
Classifier: License :: OSI Approved :: GNU General Public License v3 (GPLv3)
Requires-Dist: numpy
Requires-Dist: pandas
Requires-Dist: matplotlib
Requires-Dist: sklearn
Requires-Dist: hyperopt
Requires-Dist: xgboost
Requires-Dist: lightgbm
Requires-Dist: catboost
